StereoChemDecoder/__init__.py
StereoChemDecoder/decoder.py
stereochemdecoder-0.1.0.dist-info/licenses/LICENSE
stereochemdecoder-0.1.0.dist-info/METADATA
stereochemdecoder-0.1.0.dist-info/WHEEL
stereochemdecoder-0.1.0.dist-info/top_level.txt
stereochemdecoder-0.1.0.dist-info/RECORD
