Metadata-Version: 2.4
Name: StereoChemDecoder
Version: 0.1.0
Summary: A Python package to detect chiral centers and E/Z double bonds in SMILES strings.
Author-email: Siva Sathyaseelan D N <dnsiva.sathyaseelan.chy21@itbhu.ac.in>
License: MIT License
Requires-Python: >=3.7
License-File: LICENSE
Requires-Dist: rdkit>=2023.3.1
Dynamic: license-file
